multistructlog.py
multistructlog-1.1.dist-info/DESCRIPTION.rst
multistructlog-1.1.dist-info/METADATA
multistructlog-1.1.dist-info/RECORD
multistructlog-1.1.dist-info/WHEEL
multistructlog-1.1.dist-info/metadata.json
multistructlog-1.1.dist-info/top_level.txt
